langchain_provider/__init__.py
langchain_provider/client.py
langchain_provider/provider.py
langchain_provider/images/dark/langchain.svg
langchain_provider/images/light/langchain.svg
langchain_provider/widgets/__init__.py
langchain_provider/widgets/config_dialog.py
langchain_provider/widgets/status.py
langchain_provider-0.1.0.dist-info/LICENSE
langchain_provider-0.1.0.dist-info/METADATA
langchain_provider-0.1.0.dist-info/NOTICE.txt
langchain_provider-0.1.0.dist-info/WHEEL
langchain_provider-0.1.0.dist-info/entry_points.txt
langchain_provider-0.1.0.dist-info/top_level.txt
langchain_provider-0.1.0.dist-info/RECORD
