Metadata-Version: 2.1
Name: langchain-provider
Version: 0.1.0
Summary: Langchain provider for Spyder
Author-email: Spyder Project Contributors <spyder.python@gmail.com>
License: MIT license
Project-URL: Homepage, https://github.com/spyder-ide/langchain-provider
Classifier: Development Status :: 3 - Alpha
Classifier: Intended Audience :: Developers
Classifier: Intended Audience :: Education
Classifier: Intended Audience :: Science/Research
Classifier: Operating System :: OS Independent
Classifier: Programming Language :: Python :: 3
Classifier: Programming Language :: Python :: 3.10
Classifier: Programming Language :: Python :: 3.8
Classifier: Programming Language :: Python :: 3.9
Classifier: Topic :: Scientific/Engineering
Classifier: Topic :: Text Editors :: Integrated Development Environments (IDE)
Requires-Python: >=3.8
License-File: LICENSE
License-File: NOTICE.txt
Requires-Dist: langchain
Requires-Dist: langchain-community
Requires-Dist: openai
Requires-Dist: qtawesome
Requires-Dist: qtpy
Requires-Dist: spyder >=6.0.0a3
Provides-Extra: extras
Requires-Dist: pre-commit ; extra == 'extras'
